pyplagiarism
