Metadata-Version: 1.0
Name: pyplagiarism
Version: 0.1.2
Summary: Plagiarism Tool for Source Code
Home-page: https://github.com/julesy89/pyplagiarism
Author: Julian Blank
Author-email: blankjul@egr.msu.edu
License: Apache License 2.0
Keywords: optimization
Platform: any
